<?xml version = "1.0" encoding = "UTF-8" ?>
<Computer id="Karma"
          name="Karma"
          security="12"
          allowsDefaultBootModule="true"
          icon="chip"
          type="1" >

  <portsForCrack val="9" />
  <ports>21, 22, 104, 25, 1433, 443, 192, 554, 6881, 80</ports>
  <firewall level="7" solution="BrkoenH1art" additionalTime="0.5"/>
  <trace time="155" />
  <proxy time="2.3" />
  <file path="sys" name="Base.dll">#BINARY##BINARY_SMALL#</file>
  <file path="sys" name="config.sys">#BINARY##BINARY_SMALL#</file>
  <file path="sys" name="Tracking.dll">#BINARY##BINARY_SMALL#</file>
  <file path="sys" name="Launcher.exe">#BINARY##BINARY_SMALL#</file>
  <file path="sys" name="Heart.dll">#BINARY##BINARY_SMALL#</file>
</Computer>